quick_anomaly_detector/__init__.py
quick_anomaly_detector/data_process.py
quick_anomaly_detector/models.py
quick_anomaly_detector/pipelineClass.py
quick_anomaly_detector-0.3.5.dist-info/LICENSE
quick_anomaly_detector-0.3.5.dist-info/METADATA
quick_anomaly_detector-0.3.5.dist-info/WHEEL
quick_anomaly_detector-0.3.5.dist-info/top_level.txt
quick_anomaly_detector-0.3.5.dist-info/RECORD
