Metadata-Version: 2.1
Name: quick-anomaly-detector
Version: 0.3.5
Summary: models class for quick Anomaly Detection
Home-page: https://github.com/cheerzhang/AnomalyDetectionModel
Author: ZhangLe
Author-email: zhangle@gmail.com
Project-URL: Bug Tracker, https://github.com/cheerzhang/AnomalyDetectionModel/issues
Classifier: Programming Language :: Python :: 3
Classifier: License :: OSI Approved :: MIT License
Classifier: Operating System :: OS Independent
Requires-Python: >=3.11.2
License-File: LICENSE
Requires-Dist: pandas >=0.25.1
Requires-Dist: numpy >=1.21.5
Requires-Dist: plotly >=5.18.0
Requires-Dist: matplotlib >=3.7.1
Requires-Dist: SciPy >=1.11.4
Requires-Dist: cdifflib >=1.2.6
Requires-Dist: torch >=2.2.0
Requires-Dist: scikit-learn >=1.4.0
Requires-Dist: xgboost >=2.0.3
Requires-Dist: mlflow >=2.10.2
